aioworkers_orm/__init__.py
aioworkers_orm/factory.py
aioworkers_orm/models.py
aioworkers_orm/utils.py
aioworkers_orm-0.1.0.dist-info/LICENSE
aioworkers_orm-0.1.0.dist-info/WHEEL
aioworkers_orm-0.1.0.dist-info/METADATA
aioworkers_orm-0.1.0.dist-info/RECORD
